forta_bot_sdk/__init__.py
forta_bot_sdk/di.py
forta_bot_sdk/alerts/__init__.py
forta_bot_sdk/alerts/alert.py
forta_bot_sdk/alerts/alert_event.py
forta_bot_sdk/alerts/alert_subscription.py
forta_bot_sdk/alerts/create_alert_event.py
forta_bot_sdk/alerts/di.py
forta_bot_sdk/alerts/get_alert.py
forta_bot_sdk/alerts/get_alerts.py
forta_bot_sdk/alerts/send_alerts.py
forta_bot_sdk/blocks/__init__.py
forta_bot_sdk/blocks/block.py
forta_bot_sdk/blocks/block_event.py
forta_bot_sdk/blocks/create_block_event.py
forta_bot_sdk/blocks/di.py
forta_bot_sdk/blocks/get_block_with_transactions.py
forta_bot_sdk/blocks/get_latest_block_number.py
forta_bot_sdk/cache/__init__.py
forta_bot_sdk/cache/cache.py
forta_bot_sdk/cache/di.py
forta_bot_sdk/cache/disk_cache.py
forta_bot_sdk/cache/get_json_rpc_cache_provider.py
forta_bot_sdk/cache/is_cache_healthy.py
forta_bot_sdk/cache/json_rpc_cache.py
forta_bot_sdk/cli/__init__.py
forta_bot_sdk/cli/di.py
forta_bot_sdk/cli/run_alert.py
forta_bot_sdk/cli/run_block.py
forta_bot_sdk/cli/run_block_range.py
forta_bot_sdk/cli/run_cli_command.py
forta_bot_sdk/cli/run_transaction.py
forta_bot_sdk/common/__init__.py
forta_bot_sdk/common/handle_alert.py
forta_bot_sdk/common/handle_block.py
forta_bot_sdk/common/handle_transaction.py
forta_bot_sdk/common/health_check.py
forta_bot_sdk/common/initialize.py
forta_bot_sdk/common/scan_alerts_options.py
forta_bot_sdk/common/scan_evm_options.py
forta_bot_sdk/findings/__init__.py
forta_bot_sdk/findings/finding.py
forta_bot_sdk/findings/finding_severity.py
forta_bot_sdk/findings/finding_source.py
forta_bot_sdk/findings/finding_type.py
forta_bot_sdk/handlers/__init__.py
forta_bot_sdk/handlers/di.py
forta_bot_sdk/handlers/run_handlers_on_alert.py
forta_bot_sdk/handlers/run_handlers_on_block.py
forta_bot_sdk/handlers/run_handlers_on_transaction.py
forta_bot_sdk/health/__init__.py
forta_bot_sdk/health/di.py
forta_bot_sdk/health/run_health_check.py
forta_bot_sdk/jwt/__init__.py
forta_bot_sdk/jwt/constants.py
forta_bot_sdk-0.2.3.dist-info/LICENSE
forta_bot_sdk-0.2.3.dist-info/METADATA
forta_bot_sdk-0.2.3.dist-info/WHEEL
forta_bot_sdk-0.2.3.dist-info/top_level.txt
forta_bot_sdk-0.2.3.dist-info/RECORD
