Metadata-Version: 2.1
Name: forta_bot_sdk
Version: 0.2.3
Summary: Forta Detection Bot Python SDK
Home-page: https://forta.org/
Project-URL: Source, https://github.com/forta-network/forta-bot-sdk-v2
Project-URL: Documentation, https://docs.forta.network/
Classifier: Programming Language :: Python :: 3
Classifier: License :: OSI Approved :: MIT License
Classifier: Operating System :: OS Independent
Requires-Python: >=3.10
License-File: LICENSE
Requires-Dist: jsonc-parser
Requires-Dist: web3 ==6.13.0
Requires-Dist: hexbytes
Requires-Dist: mmh3 ==3.0.0
Requires-Dist: dependency-injector ==4.41.0
Requires-Dist: aiohttp ==3.9.2
Requires-Dist: pickleDB ==0.9.2
Requires-Dist: pylru ==1.2.1
